<!--
Shifts in um, rotations in mrad.

For more details see RPAlignmentCorrections::LoadXMLFile in
Geometry/TotemRPAlignmentDataFormats/src/RPAlignmentCorrections.cc
-->

<xml DocumentType="AlignmentDescription">
	<rp  id=" 120"                                   sh_x="  -41.25" sh_y="  +90.64" sh_x_e="   +0.33" sh_y_e="   +0.33" rot_z="  -3.165" rot_z_e="  +0.033" sh_z="   +0.00" sh_z_e="   +0.00"/>
	<det id="1200" sh_r=" +130.89" sh_r_e="   +0.58" sh_x="  -92.22" sh_y="  +92.89" sh_x_e="   -0.41" sh_y_e="   +0.41" rot_z="  -0.505" rot_z_e="  +0.101" sh_z="   +0.00" sh_z_e="   +0.00"/>
	<det id="1201" sh_r="  +69.13" sh_r_e="   +0.87" sh_x="  +49.01" sh_y="  +48.75" sh_x_e="   +0.62" sh_y_e="   +0.61" rot_z="  +0.485" rot_z_e="  +0.111" sh_z="   +0.00" sh_z_e="   +0.00"/>
	<det id="1202" sh_r="  +53.94" sh_r_e="   +0.58" sh_x="  -38.02" sh_y="  +38.27" sh_x_e="   -0.41" sh_y_e="   +0.41" rot_z="  -0.187" rot_z_e="  +0.101" sh_z="   +0.00" sh_z_e="   +0.00"/>
	<det id="1203" sh_r="  +34.35" sh_r_e="   +0.87" sh_x="  +24.36" sh_y="  +24.22" sh_x_e="   +0.62" sh_y_e="   +0.61" rot_z="  +0.332" rot_z_e="  +0.110" sh_z="   +0.00" sh_z_e="   +0.00"/>
	<det id="1204" sh_r="   +3.20" sh_r_e="   +0.58" sh_x="   -2.25" sh_y="   +2.27" sh_x_e="   -0.41" sh_y_e="   +0.41" rot_z="  +0.163" rot_z_e="  +0.101" sh_z="   +0.00" sh_z_e="   +0.00"/>
	<det id="1205" sh_r="   +7.53" sh_r_e="   +0.87" sh_x="   +5.34" sh_y="   +5.31" sh_x_e="   +0.62" sh_y_e="   +0.61" rot_z="  -0.068" rot_z_e="  +0.110" sh_z="   +0.00" sh_z_e="   +0.00"/>
	<det id="1206" sh_r="  -73.20" sh_r_e="   +0.57" sh_x="  +51.61" sh_y="  -51.91" sh_x_e="   -0.41" sh_y_e="   +0.41" rot_z="  +0.172" rot_z_e="  +0.101" sh_z="   +0.00" sh_z_e="   +0.00"/>
	<det id="1207" sh_r="  -58.53" sh_r_e="   +0.87" sh_x="  -41.55" sh_y="  -41.22" sh_x_e="   +0.62" sh_y_e="   +0.61" rot_z="  -0.781" rot_z_e="  +0.110" sh_z="   +0.00" sh_z_e="   +0.00"/>
	<det id="1208" sh_r=" -114.91" sh_r_e="   +0.57" sh_x="  +81.02" sh_y="  -81.48" sh_x_e="   -0.40" sh_y_e="   +0.41" rot_z="  +0.297" rot_z_e="  +0.100" sh_z="   +0.00" sh_z_e="   +0.00"/>
	<det id="1209" sh_r="  -52.60" sh_r_e="   +0.87" sh_x="  -37.31" sh_y="  -37.08" sh_x_e="   +0.61" sh_y_e="   +0.61" rot_z="  +0.093" rot_z_e="  +0.110" sh_z="   +0.00" sh_z_e="   +0.00"/>

	<rp  id=" 121"                                   sh_x="  +41.28" sh_y="  -90.61" sh_x_e="   +0.36" sh_y_e="   +0.36" rot_z="  +4.672" rot_z_e="  +0.042" sh_z="   +0.00" sh_z_e="   +0.00"/>
	<det id="1210" sh_r="  -87.41" sh_r_e="   +0.86" sh_x="  -62.05" sh_y="  +61.56" sh_x_e="   +0.61" sh_y_e="   -0.61" rot_z="  -0.593" rot_z_e="  +0.159" sh_z="   +0.00" sh_z_e="   +0.00"/>
	<det id="1211" sh_r="  -88.09" sh_r_e="   +0.70" sh_x="  +61.99" sh_y="  +62.58" sh_x_e="   -0.49" sh_y_e="   -0.50" rot_z="  +0.053" rot_z_e="  +0.100" sh_z="   +0.00" sh_z_e="   +0.00"/>
	<det id="1212" sh_r="  -60.45" sh_r_e="   +1.05" sh_x="  -42.92" sh_y="  +42.56" sh_x_e="   +0.75" sh_y_e="   -0.74" rot_z="  -0.353" rot_z_e="  +0.165" sh_z="   +0.00" sh_z_e="   +0.00"/>
	<det id="1213" sh_r="  -42.92" sh_r_e="   +0.70" sh_x="  +30.20" sh_y="  +30.50" sh_x_e="   -0.49" sh_y_e="   -0.50" rot_z="  +0.238" rot_z_e="  +0.100" sh_z="   +0.00" sh_z_e="   +0.00"/>
	<det id="1214" sh_r="  +11.90" sh_r_e="   +0.86" sh_x="   +8.46" sh_y="   -8.37" sh_x_e="   +0.61" sh_y_e="   -0.61" rot_z="  +1.202" rot_z_e="  +0.159" sh_z="   +0.00" sh_z_e="   +0.00"/>
	<det id="1215" sh_r="  -21.95" sh_r_e="   +0.70" sh_x="  +15.46" sh_y="  +15.58" sh_x_e="   -0.49" sh_y_e="   -0.50" rot_z="  -0.729" rot_z_e="  +0.100" sh_z="   +0.00" sh_z_e="   +0.00"/>
	<det id="1216" sh_r="  +47.95" sh_r_e="   +0.86" sh_x="  +34.03" sh_y="  -33.78" sh_x_e="   +0.61" sh_y_e="   -0.61" rot_z="  -0.745" rot_z_e="  +0.158" sh_z="   +0.00" sh_z_e="   +0.00"/>
	<det id="1217" sh_r="  +65.02" sh_r_e="   +0.71" sh_x="  -45.71" sh_y="  -46.24" sh_x_e="   -0.50" sh_y_e="   -0.50" rot_z="  +1.052" rot_z_e="  +0.108" sh_z="   +0.00" sh_z_e="   +0.00"/>
	<det id="1218" sh_r="  +87.95" sh_r_e="   +0.86" sh_x="  +62.46" sh_y="  -61.92" sh_x_e="   +0.61" sh_y_e="   -0.61" rot_z="  -0.151" rot_z_e="  +0.158" sh_z="   +0.00" sh_z_e="   +0.00"/>
	<det id="1219" sh_r="  +87.97" sh_r_e="   +0.70" sh_x="  -61.91" sh_y="  -62.49" sh_x_e="   -0.49" sh_y_e="   -0.50" rot_z="  +0.026" rot_z_e="  +0.099" sh_z="   +0.00" sh_z_e="   +0.00"/>

	<rp  id=" 122"                                   sh_x="  -83.54" sh_y=" +714.54" sh_x_e="   +0.32" sh_y_e="   +0.32" rot_z="  -1.507" rot_z_e="  +0.021" sh_z="   +0.00" sh_z_e="   +0.00"/>
	<det id="1220" sh_r="  +48.36" sh_r_e="   +0.65" sh_x="  +34.24" sh_y="  +34.15" sh_x_e="   +0.46" sh_y_e="   +0.46" rot_z="  +0.144" rot_z_e="  +0.056" sh_z="   +0.00" sh_z_e="   +0.00"/>
	<det id="1221" sh_r="  +74.61" sh_r_e="   +0.80" sh_x="  +52.68" sh_y="  -52.84" sh_x_e="   +0.56" sh_y_e="   -0.56" rot_z="  -0.018" rot_z_e="  +0.074" sh_z="   +0.00" sh_z_e="   +0.00"/>
	<det id="1222" sh_r="  +40.10" sh_r_e="   +0.65" sh_x="  +28.39" sh_y="  +28.31" sh_x_e="   +0.46" sh_y_e="   +0.46" rot_z="  +0.162" rot_z_e="  +0.056" sh_z="   +0.00" sh_z_e="   +0.00"/>
	<det id="1223" sh_r="  +65.43" sh_r_e="   +0.80" sh_x="  +46.23" sh_y="  -46.31" sh_x_e="   +0.56" sh_y_e="   -0.56" rot_z="  +0.581" rot_z_e="  +0.074" sh_z="   +0.00" sh_z_e="   +0.00"/>
	<det id="1224" sh_r="   -3.42" sh_r_e="   +0.65" sh_x="   -2.42" sh_y="   -2.41" sh_x_e="   +0.46" sh_y_e="   +0.46" rot_z="  -0.571" rot_z_e="  +0.055" sh_z="   +0.00" sh_z_e="   +0.00"/>
	<det id="1225" sh_r="   -7.86" sh_r_e="   +0.79" sh_x="   -5.55" sh_y="   +5.57" sh_x_e="   +0.56" sh_y_e="   -0.56" rot_z="  -0.249" rot_z_e="  +0.074" sh_z="   +0.00" sh_z_e="   +0.00"/>
	<det id="1226" sh_r="  -30.76" sh_r_e="   +0.65" sh_x="  -21.79" sh_y="  -21.71" sh_x_e="   +0.46" sh_y_e="   +0.46" rot_z="  -0.134" rot_z_e="  +0.055" sh_z="   +0.00" sh_z_e="   +0.00"/>
	<det id="1227" sh_r="  -51.63" sh_r_e="   +0.79" sh_x="  -36.46" sh_y="  +36.56" sh_x_e="   +0.56" sh_y_e="   -0.56" rot_z="  +0.045" rot_z_e="  +0.074" sh_z="   +0.00" sh_z_e="   +0.00"/>
	<det id="1228" sh_r="  -54.29" sh_r_e="   +0.65" sh_x="  -38.46" sh_y="  -38.32" sh_x_e="   +0.46" sh_y_e="   +0.46" rot_z="  -0.302" rot_z_e="  +0.055" sh_z="   +0.00" sh_z_e="   +0.00"/>
	<det id="1229" sh_r="  -80.52" sh_r_e="   +0.79" sh_x="  -56.87" sh_y="  +57.00" sh_x_e="   +0.56" sh_y_e="   -0.56" rot_z="  +0.342" rot_z_e="  +0.074" sh_z="   +0.00" sh_z_e="   +0.00"/>

	<rp  id=" 123"                                   sh_x=" +828.02" sh_y=" +726.92" sh_x_e="   +0.31" sh_y_e="   +0.31" rot_z="  -2.616" rot_z_e="  +0.020" sh_z="   +0.00" sh_z_e="   +0.00"/>
	<det id="1230" sh_r="  +20.89" sh_r_e="   +0.62" sh_x="  +14.82" sh_y="  +14.72" sh_x_e="   +0.44" sh_y_e="   +0.44" rot_z="  -0.735" rot_z_e="  +0.055" sh_z="   +0.00" sh_z_e="   +0.00"/>
	<det id="1231" sh_r="  +49.85" sh_r_e="   +0.76" sh_x="  +35.18" sh_y="  -35.32" sh_x_e="   +0.53" sh_y_e="   -0.54" rot_z="  +0.483" rot_z_e="  +0.072" sh_z="   +0.00" sh_z_e="   +0.00"/>
	<det id="1232" sh_r="  +33.85" sh_r_e="   +0.63" sh_x="  +24.00" sh_y="  +23.87" sh_x_e="   +0.44" sh_y_e="   +0.44" rot_z="  -0.156" rot_z_e="  +0.055" sh_z="   +0.00" sh_z_e="   +0.00"/>
	<det id="1233" sh_r="   +9.79" sh_r_e="   +0.76" sh_x="   +6.90" sh_y="   -6.94" sh_x_e="   +0.54" sh_y_e="   -0.54" rot_z="  -0.487" rot_z_e="  +0.072" sh_z="   +0.00" sh_z_e="   +0.00"/>
	<det id="1234" sh_r="  +23.07" sh_r_e="   +0.63" sh_x="  +16.36" sh_y="  +16.27" sh_x_e="   +0.44" sh_y_e="   +0.44" rot_z="  -0.466" rot_z_e="  +0.055" sh_z="   +0.00" sh_z_e="   +0.00"/>
	<det id="1235" sh_r="   -8.16" sh_r_e="   +0.76" sh_x="   -5.76" sh_y="   +5.78" sh_x_e="   +0.54" sh_y_e="   -0.54" rot_z="  +0.300" rot_z_e="  +0.072" sh_z="   +0.00" sh_z_e="   +0.00"/>
	<det id="1236" sh_r="  -13.81" sh_r_e="   +0.63" sh_x="   -9.79" sh_y="   -9.74" sh_x_e="   +0.45" sh_y_e="   +0.44" rot_z="  -0.168" rot_z_e="  +0.055" sh_z="   +0.00" sh_z_e="   +0.00"/>
	<det id="1237" sh_r="  -30.24" sh_r_e="   +0.76" sh_x="  -21.33" sh_y="  +21.43" sh_x_e="   +0.54" sh_y_e="   -0.54" rot_z="  +0.222" rot_z_e="  +0.072" sh_z="   +0.00" sh_z_e="   +0.00"/>
	<det id="1238" sh_r="  -64.00" sh_r_e="   +0.63" sh_x="  -45.35" sh_y="  -45.16" sh_x_e="   +0.45" sh_y_e="   +0.44" rot_z="  +0.459" rot_z_e="  +0.055" sh_z="   +0.00" sh_z_e="   +0.00"/>
	<det id="1239" sh_r="  -21.30" sh_r_e="   +0.76" sh_x="  -15.03" sh_y="  +15.09" sh_x_e="   +0.54" sh_y_e="   -0.54" rot_z="  +0.548" rot_z_e="  +0.072" sh_z="   +0.00" sh_z_e="   +0.00"/>

	<rp  id=" 124"                                   sh_x="  -35.49" sh_y=" +202.12" sh_x_e="   +0.31" sh_y_e="   +0.31" rot_z="  -4.312" rot_z_e="  +0.033" sh_z="   +0.00" sh_z_e="   +0.00"/>
	<det id="1240" sh_r="  +48.26" sh_r_e="   +0.56" sh_x="  -33.96" sh_y="  +34.29" sh_x_e="   -0.40" sh_y_e="   +0.40" rot_z="  -0.686" rot_z_e="  +0.097" sh_z="   +0.00" sh_z_e="   +0.00"/>
	<det id="1241" sh_r="  +35.82" sh_r_e="   +0.80" sh_x="  +25.46" sh_y="  +25.20" sh_x_e="   +0.57" sh_y_e="   +0.56" rot_z="  -0.593" rot_z_e="  +0.110" sh_z="   +0.00" sh_z_e="   +0.00"/>
	<det id="1242" sh_r="  +22.40" sh_r_e="   +0.56" sh_x="  -15.75" sh_y="  +15.92" sh_x_e="   -0.40" sh_y_e="   +0.40" rot_z="  -1.253" rot_z_e="  +0.097" sh_z="   +0.00" sh_z_e="   +0.00"/>
	<det id="1243" sh_r="  +32.37" sh_r_e="   +0.80" sh_x="  +22.99" sh_y="  +22.78" sh_x_e="   +0.57" sh_y_e="   +0.56" rot_z="  -0.322" rot_z_e="  +0.110" sh_z="   +0.00" sh_z_e="   +0.00"/>
	<det id="1244" sh_r="   +7.87" sh_r_e="   +0.56" sh_x="   -5.54" sh_y="   +5.59" sh_x_e="   -0.40" sh_y_e="   +0.40" rot_z="  +0.211" rot_z_e="  +0.097" sh_z="   +0.00" sh_z_e="   +0.00"/>
	<det id="1245" sh_r="  +23.82" sh_r_e="   +0.80" sh_x="  +16.91" sh_y="  +16.78" sh_x_e="   +0.57" sh_y_e="   +0.56" rot_z="  +0.533" rot_z_e="  +0.110" sh_z="   +0.00" sh_z_e="   +0.00"/>
	<det id="1246" sh_r="  -32.63" sh_r_e="   +0.56" sh_x="  +22.98" sh_y="  -23.17" sh_x_e="   -0.40" sh_y_e="   +0.40" rot_z="  +0.165" rot_z_e="  +0.097" sh_z="   +0.00" sh_z_e="   +0.00"/>
	<det id="1247" sh_r="  -44.26" sh_r_e="   +0.80" sh_x="  -31.42" sh_y="  -31.17" sh_x_e="   +0.57" sh_y_e="   +0.56" rot_z="  +0.243" rot_z_e="  +0.110" sh_z="   +0.00" sh_z_e="   +0.00"/>
	<det id="1248" sh_r="  -45.83" sh_r_e="   +0.56" sh_x="  +32.31" sh_y="  -32.51" sh_x_e="   -0.40" sh_y_e="   +0.40" rot_z="  +1.022" rot_z_e="  +0.097" sh_z="   +0.00" sh_z_e="   +0.00"/>
	<det id="1249" sh_r="  -47.86" sh_r_e="   +0.80" sh_x="  -33.97" sh_y="  -33.72" sh_x_e="   +0.57" sh_y_e="   +0.56" rot_z="  +0.681" rot_z_e="  +0.110" sh_z="   +0.00" sh_z_e="   +0.00"/>

	<rp  id=" 125"                                   sh_x="  +35.54" sh_y=" -202.09" sh_x_e="   +0.32" sh_y_e="   +0.32" rot_z="  +6.930" rot_z_e="  +0.040" sh_z="   +0.00" sh_z_e="   +0.00"/>
	<det id="1250" sh_r="  -93.86" sh_r_e="   +0.77" sh_x="  -66.74" sh_y="  +66.01" sh_x_e="   +0.55" sh_y_e="   -0.54" rot_z="  -1.342" rot_z_e="  +0.152" sh_z="   +0.00" sh_z_e="   +0.00"/>
	<det id="1251" sh_r="  -21.00" sh_r_e="   +0.65" sh_x="  +14.76" sh_y="  +14.94" sh_x_e="   -0.46" sh_y_e="   -0.46" rot_z="  -0.808" rot_z_e="  +0.094" sh_z="   +0.00" sh_z_e="   +0.00"/>
	<det id="1252" sh_r="  -47.72" sh_r_e="   +0.78" sh_x="  -33.96" sh_y="  +33.53" sh_x_e="   +0.55" sh_y_e="   -0.54" rot_z="  -0.595" rot_z_e="  +0.152" sh_z="   +0.00" sh_z_e="   +0.00"/>
	<det id="1253" sh_r="   -7.03" sh_r_e="   +0.65" sh_x="   +4.94" sh_y="   +5.00" sh_x_e="   -0.46" sh_y_e="   -0.47" rot_z="  -0.526" rot_z_e="  +0.094" sh_z="   +0.00" sh_z_e="   +0.00"/>
	<det id="1254" sh_r="  +28.97" sh_r_e="   +0.77" sh_x="  +20.62" sh_y="  -20.35" sh_x_e="   +0.55" sh_y_e="   -0.54" rot_z="  -0.181" rot_z_e="  +0.153" sh_z="   +0.00" sh_z_e="   +0.00"/>
	<det id="1255" sh_r="  -11.11" sh_r_e="   +0.66" sh_x="   +7.80" sh_y="   +7.91" sh_x_e="   -0.46" sh_y_e="   -0.47" rot_z="  -0.016" rot_z_e="  +0.094" sh_z="   +0.00" sh_z_e="   +0.00"/>
	<det id="1256" sh_r="  +36.15" sh_r_e="   +0.78" sh_x="  +25.74" sh_y="  -25.38" sh_x_e="   +0.55" sh_y_e="   -0.54" rot_z="  +0.323" rot_z_e="  +0.153" sh_z="   +0.00" sh_z_e="   +0.00"/>
	<det id="1257" sh_r="  +19.86" sh_r_e="   +0.66" sh_x="  -13.93" sh_y="  -14.15" sh_x_e="   -0.46" sh_y_e="   -0.47" rot_z="  +0.849" rot_z_e="  +0.094" sh_z="   +0.00" sh_z_e="   +0.00"/>
	<det id="1258" sh_r="  +76.40" sh_r_e="   +0.78" sh_x="  +54.45" sh_y="  -53.59" sh_x_e="   +0.55" sh_y_e="   -0.54" rot_z="  +1.272" rot_z_e="  +0.153" sh_z="   +0.00" sh_z_e="   +0.00"/>
	<det id="1259" sh_r="  +19.51" sh_r_e="   +0.66" sh_x="  -13.69" sh_y="  -13.91" sh_x_e="   -0.46" sh_y_e="   -0.47" rot_z="  +1.026" rot_z_e="  +0.094" sh_z="   +0.00" sh_z_e="   +0.00"/>
</xml>
